FriendlyHandbook/__init__.py
FriendlyHandbook/adbook.py
FriendlyHandbook/calculator.py
FriendlyHandbook/main.py
FriendlyHandbook/note_book.py
FriendlyHandbook/prompt_tool.py
FriendlyHandbook/sort_folder.py
FriendlyHandbook-0.1.2.dist-info/LICENSE
FriendlyHandbook-0.1.2.dist-info/METADATA
FriendlyHandbook-0.1.2.dist-info/WHEEL
FriendlyHandbook-0.1.2.dist-info/entry_points.txt
FriendlyHandbook-0.1.2.dist-info/top_level.txt
FriendlyHandbook-0.1.2.dist-info/RECORD
