Metadata-Version: 2.1
Name: FriendlyHandbook
Version: 0.1.2
Summary: «FriendlyHandbook» - це корисна програма з інтерфейсом командного рядка, яка містить контактну книгу, нотатки, калькулятор та може аналізувати папки.
Home-page: https://github.com/filinmbg/FriendlyHandbook
Author: JustPython
Author-email: filinmbg@gmail.com
License: MIT
License-File: LICENSE
Requires-Dist: prompt-toolkit ==3.0.39
